{
  "timestamp": "2026-04-01T03:29:56.053222+00:00",
  "stage": 3,
  "csv_path": "/home/kyudev/Documents/chrono_pendulum_final/host/run_logs/chrono_run_3.csv",
  "excitation_type": "burst",
  "model_type": "pytorch_gru_black_box_dynamics",
  "theta_source": "theta_real",
  "omega_source": "omega_real",
  "input_source": "hw_pwm",
  "target_type": "theta_next_omega_next",
  "sequence_length": 32,
  "rollout_horizon": 5,
  "normalization_method": "zscore_per_feature",
  "training_loss": 0.0015820616032355106,
  "validation_loss": 0.001504797488451004,
  "best_validation_loss": 0.0006790799779992085,
  "checkpoint_path": "/home/kyudev/Documents/chrono_pendulum_final/host/run_logs/stage3/gru_dynamics.pt",
  "plot_paths": {
    "fit_summary": "/home/kyudev/Documents/chrono_pendulum_final/host/run_logs/stage3/stage3_fit_summary.png",
    "overlay": "/home/kyudev/Documents/chrono_pendulum_final/host/run_logs/stage3/stage3_theta_omega_alpha_overlay.png",
    "loss_convergence": "/home/kyudev/Documents/chrono_pendulum_final/host/run_logs/stage3/stage3_loss_convergence.png"
  },
  "loss_history_csv": "/home/kyudev/Documents/chrono_pendulum_final/host/run_logs/stage3/stage3_loss_history.csv",
  "epoch_logs": [
    {
      "epoch": 1,
      "train_loss": 0.012569115747912573,
      "val_loss": 0.0016485657179146074
    },
    {
      "epoch": 2,
      "train_loss": 0.003947884793608234,
      "val_loss": 0.0021076486445963383
    },
    {
      "epoch": 3,
      "train_loss": 0.0028586738581697527,
      "val_loss": 0.0008941160176618723
    },
    {
      "epoch": 4,
      "train_loss": 0.0023887651220250586,
      "val_loss": 0.0014058527303859591
    },
    {
      "epoch": 5,
      "train_loss": 0.0021382695816170713,
      "val_loss": 0.0012951241951668635
    },
    {
      "epoch": 6,
      "train_loss": 0.002053890932494631,
      "val_loss": 0.0012120652390876785
    },
    {
      "epoch": 7,
      "train_loss": 0.001948837898313426,
      "val_loss": 0.0010928415867965668
    },
    {
      "epoch": 8,
      "train_loss": 0.0019225993175775958,
      "val_loss": 0.0010812546097440645
    },
    {
      "epoch": 9,
      "train_loss": 0.0020190917242031833,
      "val_loss": 0.0014158062695059925
    },
    {
      "epoch": 10,
      "train_loss": 0.0019299687119200826,
      "val_loss": 0.0009887369305943139
    },
    {
      "epoch": 11,
      "train_loss": 0.0018415384424420504,
      "val_loss": 0.0012541111063910648
    },
    {
      "epoch": 12,
      "train_loss": 0.0018703274948235888,
      "val_loss": 0.0014523001154884696
    },
    {
      "epoch": 13,
      "train_loss": 0.0019365919646448814,
      "val_loss": 0.0014445865526795387
    },
    {
      "epoch": 14,
      "train_loss": 0.0018107711355416821,
      "val_loss": 0.001182078180136159
    },
    {
      "epoch": 15,
      "train_loss": 0.0017018799687950658,
      "val_loss": 0.0009696437482489273
    },
    {
      "epoch": 16,
      "train_loss": 0.0017979027470573783,
      "val_loss": 0.0006790799779992085
    },
    {
      "epoch": 17,
      "train_loss": 0.0019493384662872325,
      "val_loss": 0.0017580694111529738
    },
    {
      "epoch": 18,
      "train_loss": 0.0018440852783477078,
      "val_loss": 0.001013278066238854
    },
    {
      "epoch": 19,
      "train_loss": 0.0018260874337731646,
      "val_loss": 0.0013483406510204077
    },
    {
      "epoch": 20,
      "train_loss": 0.0020148660808515092,
      "val_loss": 0.0014940265973564237
    },
    {
      "epoch": 21,
      "train_loss": 0.0019406885839998722,
      "val_loss": 0.001886397076305002
    },
    {
      "epoch": 22,
      "train_loss": 0.0018482664689564933,
      "val_loss": 0.0016979174106381834
    },
    {
      "epoch": 23,
      "train_loss": 0.001713385832352707,
      "val_loss": 0.0008906788789317943
    },
    {
      "epoch": 24,
      "train_loss": 0.0018216200047530807,
      "val_loss": 0.0016391605895478278
    },
    {
      "epoch": 25,
      "train_loss": 0.0018221307456350098,
      "val_loss": 0.0008379394803341711
    },
    {
      "epoch": 26,
      "train_loss": 0.0019056125132080454,
      "val_loss": 0.0009556346121826209
    },
    {
      "epoch": 27,
      "train_loss": 0.002063123992859171,
      "val_loss": 0.001568084437167272
    },
    {
      "epoch": 28,
      "train_loss": 0.0018867252018445958,
      "val_loss": 0.0007446271665685344
    },
    {
      "epoch": 29,
      "train_loss": 0.001727179973386228,
      "val_loss": 0.0007744229424133664
    },
    {
      "epoch": 30,
      "train_loss": 0.0018253077376777162,
      "val_loss": 0.0009278940851800144
    },
    {
      "epoch": 31,
      "train_loss": 0.0017686261025329048,
      "val_loss": 0.0010066039285447914
    },
    {
      "epoch": 32,
      "train_loss": 0.001740839878598658,
      "val_loss": 0.0007425107032759115
    },
    {
      "epoch": 33,
      "train_loss": 0.0017916047676967888,
      "val_loss": 0.0008470065313304076
    },
    {
      "epoch": 34,
      "train_loss": 0.001955951635654156,
      "val_loss": 0.001993520825635642
    },
    {
      "epoch": 35,
      "train_loss": 0.0020038831728295637,
      "val_loss": 0.0009896586307149846
    },
    {
      "epoch": 36,
      "train_loss": 0.0018961303777849446,
      "val_loss": 0.001571101602166891
    },
    {
      "epoch": 37,
      "train_loss": 0.001913877329430901,
      "val_loss": 0.0008744555962039158
    },
    {
      "epoch": 38,
      "train_loss": 0.0018494355205733043,
      "val_loss": 0.0008352189834113233
    },
    {
      "epoch": 39,
      "train_loss": 0.0017992527618144567,
      "val_loss": 0.0007052764412946999
    },
    {
      "epoch": 40,
      "train_loss": 0.001698946965356859,
      "val_loss": 0.0008891407633200288
    },
    {
      "epoch": 41,
      "train_loss": 0.0019039719347627116,
      "val_loss": 0.0008153302496793913
    },
    {
      "epoch": 42,
      "train_loss": 0.0019879695028066635,
      "val_loss": 0.0011008889268850908
    },
    {
      "epoch": 43,
      "train_loss": 0.0016563752612385612,
      "val_loss": 0.0013389773084782064
    },
    {
      "epoch": 44,
      "train_loss": 0.0017392490542708682,
      "val_loss": 0.0013788342475891113
    },
    {
      "epoch": 45,
      "train_loss": 0.0016449914009381945,
      "val_loss": 0.0014931957121007144
    },
    {
      "epoch": 46,
      "train_loss": 0.0017234178242058707,
      "val_loss": 0.0012019764981232584
    },
    {
      "epoch": 47,
      "train_loss": 0.0018503071758179711,
      "val_loss": 0.001580102281877771
    },
    {
      "epoch": 48,
      "train_loss": 0.001702563980450997,
      "val_loss": 0.001316742185736075
    },
    {
      "epoch": 49,
      "train_loss": 0.001763604232110083,
      "val_loss": 0.0009623793594073504
    },
    {
      "epoch": 50,
      "train_loss": 0.0018855742572878415,
      "val_loss": 0.0019339147256687284
    },
    {
      "epoch": 51,
      "train_loss": 0.0017974730043743665,
      "val_loss": 0.0008569503697799519
    },
    {
      "epoch": 52,
      "train_loss": 0.0017369410667855006,
      "val_loss": 0.0007718415618001018
    },
    {
      "epoch": 53,
      "train_loss": 0.0016690922829394157,
      "val_loss": 0.0008319859771290794
    },
    {
      "epoch": 54,
      "train_loss": 0.0017535794848719467,
      "val_loss": 0.002077571436529979
    },
    {
      "epoch": 55,
      "train_loss": 0.0017402216415995588,
      "val_loss": 0.0016007088706828654
    },
    {
      "epoch": 56,
      "train_loss": 0.001747010938393382,
      "val_loss": 0.0010063215377158485
    },
    {
      "epoch": 57,
      "train_loss": 0.00182618684350298,
      "val_loss": 0.0008231127012550132
    },
    {
      "epoch": 58,
      "train_loss": 0.0019972142226134357,
      "val_loss": 0.001627673686016351
    },
    {
      "epoch": 59,
      "train_loss": 0.0017256906094889229,
      "val_loss": 0.001931343082105741
    },
    {
      "epoch": 60,
      "train_loss": 0.001657737042898169,
      "val_loss": 0.001172249103547074
    },
    {
      "epoch": 61,
      "train_loss": 0.0015921557877356042,
      "val_loss": 0.0011691820836858824
    },
    {
      "epoch": 62,
      "train_loss": 0.0017788663524417924,
      "val_loss": 0.0008846329619700555
    },
    {
      "epoch": 63,
      "train_loss": 0.001767087154663526,
      "val_loss": 0.0008925115544116125
    },
    {
      "epoch": 64,
      "train_loss": 0.0016840427863196684,
      "val_loss": 0.0010887238167924806
    },
    {
      "epoch": 65,
      "train_loss": 0.0016147852069340073,
      "val_loss": 0.001142709152190946
    },
    {
      "epoch": 66,
      "train_loss": 0.001649761124728964,
      "val_loss": 0.0010916934043052606
    },
    {
      "epoch": 67,
      "train_loss": 0.0016328191402583169,
      "val_loss": 0.0007751251250738278
    },
    {
      "epoch": 68,
      "train_loss": 0.001665268218717896,
      "val_loss": 0.0008678185586177278
    },
    {
      "epoch": 69,
      "train_loss": 0.0015482175020644297,
      "val_loss": 0.001167040943983011
    },
    {
      "epoch": 70,
      "train_loss": 0.00153331238274964,
      "val_loss": 0.001090196441509761
    },
    {
      "epoch": 71,
      "train_loss": 0.001675796748783726,
      "val_loss": 0.001600344927283004
    },
    {
      "epoch": 72,
      "train_loss": 0.0015531282674951048,
      "val_loss": 0.0010627196461427957
    },
    {
      "epoch": 73,
      "train_loss": 0.0016329301377901663,
      "val_loss": 0.001814719580579549
    },
    {
      "epoch": 74,
      "train_loss": 0.0015652082914199966,
      "val_loss": 0.0009367066959384829
    },
    {
      "epoch": 75,
      "train_loss": 0.001558928956420949,
      "val_loss": 0.0012089046358596534
    },
    {
      "epoch": 76,
      "train_loss": 0.0015529884168734918,
      "val_loss": 0.0014235692797228694
    },
    {
      "epoch": 77,
      "train_loss": 0.0015357405018921082,
      "val_loss": 0.0012344841816229746
    },
    {
      "epoch": 78,
      "train_loss": 0.0014722038938019138,
      "val_loss": 0.0008697024895809591
    },
    {
      "epoch": 79,
      "train_loss": 0.0015334003390027927,
      "val_loss": 0.0009526410285616294
    },
    {
      "epoch": 80,
      "train_loss": 0.001629547502558965,
      "val_loss": 0.000887321526533924
    },
    {
      "epoch": 81,
      "train_loss": 0.0015997742034065037,
      "val_loss": 0.0010537923662923276
    },
    {
      "epoch": 82,
      "train_loss": 0.0015560112750300993,
      "val_loss": 0.0009046863779076375
    },
    {
      "epoch": 83,
      "train_loss": 0.0016242181434510993,
      "val_loss": 0.0010209949905402027
    },
    {
      "epoch": 84,
      "train_loss": 0.001639259925398689,
      "val_loss": 0.0014357375912368298
    },
    {
      "epoch": 85,
      "train_loss": 0.0016115900630561204,
      "val_loss": 0.0011430945596657693
    },
    {
      "epoch": 86,
      "train_loss": 0.001708834503705685,
      "val_loss": 0.00236071104882285
    },
    {
      "epoch": 87,
      "train_loss": 0.001816815033984872,
      "val_loss": 0.0019036454323213547
    },
    {
      "epoch": 88,
      "train_loss": 0.001873911850942442,
      "val_loss": 0.002263949892949313
    },
    {
      "epoch": 89,
      "train_loss": 0.0016874990318543636,
      "val_loss": 0.002164857112802565
    },
    {
      "epoch": 90,
      "train_loss": 0.0015793883582003987,
      "val_loss": 0.0007298920645553153
    },
    {
      "epoch": 91,
      "train_loss": 0.0015549596148328139,
      "val_loss": 0.0007972386083565652
    },
    {
      "epoch": 92,
      "train_loss": 0.0015389651525765657,
      "val_loss": 0.0008291451649711234
    },
    {
      "epoch": 93,
      "train_loss": 0.001654271322947282,
      "val_loss": 0.0010486050450708717
    },
    {
      "epoch": 94,
      "train_loss": 0.0014936671896766012,
      "val_loss": 0.0013037689204793423
    },
    {
      "epoch": 95,
      "train_loss": 0.0015383577332473719,
      "val_loss": 0.0012938600266352296
    },
    {
      "epoch": 96,
      "train_loss": 0.0015680128439831047,
      "val_loss": 0.0016793617978692055
    },
    {
      "epoch": 97,
      "train_loss": 0.0015831441314031298,
      "val_loss": 0.0015742315154056996
    },
    {
      "epoch": 98,
      "train_loss": 0.0014973615672296057,
      "val_loss": 0.0014208808715920895
    },
    {
      "epoch": 99,
      "train_loss": 0.0015479890056527578,
      "val_loss": 0.0015455462562385947
    },
    {
      "epoch": 100,
      "train_loss": 0.0017591798678040504,
      "val_loss": 0.0020922527473885566
    },
    {
      "epoch": 101,
      "train_loss": 0.0017433459691416759,
      "val_loss": 0.0016947536496445537
    },
    {
      "epoch": 102,
      "train_loss": 0.0015632938772726518,
      "val_loss": 0.0014060026733204722
    },
    {
      "epoch": 103,
      "train_loss": 0.0016615161260303396,
      "val_loss": 0.0008892574151104782
    },
    {
      "epoch": 104,
      "train_loss": 0.0017126990088190024,
      "val_loss": 0.0011831480078399181
    },
    {
      "epoch": 105,
      "train_loss": 0.0017041196921267188,
      "val_loss": 0.001722786546451971
    },
    {
      "epoch": 106,
      "train_loss": 0.0016743875144479366,
      "val_loss": 0.0018187327950727195
    },
    {
      "epoch": 107,
      "train_loss": 0.0015867721611777176,
      "val_loss": 0.0020853138412348926
    },
    {
      "epoch": 108,
      "train_loss": 0.0017916077855401314,
      "val_loss": 0.0020331599516794086
    },
    {
      "epoch": 109,
      "train_loss": 0.0015108708937007647,
      "val_loss": 0.0011866745917359367
    },
    {
      "epoch": 110,
      "train_loss": 0.0015054579483918273,
      "val_loss": 0.0009596598320058547
    },
    {
      "epoch": 111,
      "train_loss": 0.0016223744202691775,
      "val_loss": 0.002552419784478843
    },
    {
      "epoch": 112,
      "train_loss": 0.0014867830591706128,
      "val_loss": 0.0017785882810130715
    },
    {
      "epoch": 113,
      "train_loss": 0.0015573118132754015,
      "val_loss": 0.0020082944247405976
    },
    {
      "epoch": 114,
      "train_loss": 0.0016219382568334157,
      "val_loss": 0.002217828994616866
    },
    {
      "epoch": 115,
      "train_loss": 0.0016701911898473133,
      "val_loss": 0.0020039501250721514
    },
    {
      "epoch": 116,
      "train_loss": 0.0015863712894945191,
      "val_loss": 0.0013474906445480883
    },
    {
      "epoch": 117,
      "train_loss": 0.0015409502935094328,
      "val_loss": 0.0009840424936555792
    },
    {
      "epoch": 118,
      "train_loss": 0.0016132736077102332,
      "val_loss": 0.0009074660156329628
    },
    {
      "epoch": 119,
      "train_loss": 0.0015679620779477633,
      "val_loss": 0.0008296220803458709
    },
    {
      "epoch": 120,
      "train_loss": 0.0015820616032355106,
      "val_loss": 0.001504797488451004
    }
  ],
  "source_policy": {
    "sim_data_used_for_fitting": false,
    "cmd_u_raw_used_for_fitting": false,
    "real_data_only": true
  }
}